aiodxf/__init__.py
aiodxf/__main__.py
aiodxf/exceptions.py
aiodxf/main.py
aiodxf-7.5.5.dist-info/LICENCE
aiodxf-7.5.5.dist-info/METADATA
aiodxf-7.5.5.dist-info/WHEEL
aiodxf-7.5.5.dist-info/entry_points.txt
aiodxf-7.5.5.dist-info/top_level.txt
aiodxf-7.5.5.dist-info/RECORD
