Metadata-Version: 2.1
Name: aiodxf
Version: 7.5.5
Summary: Package for accessing a Docker v2 registry
Home-page: https://github.com/fiveai/aiodxf
Author: FiveAI Ltd.
Author-email: will.gardner@five.ai
License: MIT
Keywords: docker registry
Platform: UNKNOWN
Requires-Dist: www-authenticate (>=0.9.2)
Requires-Dist: aiohttp (>=3.6.2)
Requires-Dist: jwcrypto (>=0.4.2)
Requires-Dist: tqdm (>=4.19.4)
